dsg_jit/__init__.py
dsg_jit/api/__init__.py
dsg_jit/api/dsg_api.py
dsg_jit/core/__init__.py
dsg_jit/core/factor_graph.py
dsg_jit/core/math3d.py
dsg_jit/core/types.py
dsg_jit/datasets/__init__.py
dsg_jit/datasets/kitti_odometry.py
dsg_jit/datasets/tum_rgbd.py
dsg_jit/optimization/__init__.py
dsg_jit/optimization/jit_wrappers.py
dsg_jit/optimization/solvers.py
dsg_jit/scene_graph/__init__.py
dsg_jit/scene_graph/entities.py
dsg_jit/scene_graph/relations.py
dsg_jit/sensors/__init__.py
dsg_jit/sensors/base.py
dsg_jit/sensors/camera.py
dsg_jit/sensors/conversion.py
dsg_jit/sensors/fusion.py
dsg_jit/sensors/imu.py
dsg_jit/sensors/integration.py
dsg_jit/sensors/lidar.py
dsg_jit/sensors/streams.py
dsg_jit/slam/__init__.py
dsg_jit/slam/manifold.py
dsg_jit/slam/measurements.py
dsg_jit/slam/pipeline.py
dsg_jit/world/dynamic_scene_graph.py
dsg_jit/world/model.py
dsg_jit/world/scene_graph.py
dsg_jit/world/training.py
dsg_jit/world/visualization.py
dsg_jit/world/voxel_grid.py
dsg_jit/world/web_viewer.py
dsg_jit-0.7.1.dist-info/METADATA
dsg_jit-0.7.1.dist-info/WHEEL
dsg_jit-0.7.1.dist-info/licenses/LICENSE
dsg_jit-0.7.1.dist-info/RECORD
