Metadata-Version: 2.4
Name: dsg_jit
Version: 0.7.1
Summary: Differentiable Scene Graphs with JAX-based factor graphs and SLAM tooling.
Project-URL: Homepage, https://github.com/tannertorrey3/DSG-JIT
Project-URL: Documentation, https://tannertorrey3.github.io/DSG-JIT/
Project-URL: Source, https://github.com/tannertorrey3/DSG-JIT
Project-URL: Issues, https://github.com/tannertorrey3/DSG-JIT/issues
Author: Tanner Kocher
License: MIT
License-File: LICENSE
Keywords: JAX,SLAM,factor-graph,optimization,robotics,scene-graph
Classifier: Development Status :: 3 - Alpha
Classifier: Intended Audience :: Developers
Classifier: Intended Audience :: Science/Research
Classifier: License :: OSI Approved :: MIT License
Classifier: Programming Language :: Python
Classifier: Programming Language :: Python :: 3
Classifier: Programming Language :: Python :: 3.9
Classifier: Programming Language :: Python :: 3.10
Classifier: Programming Language :: Python :: 3.11
Classifier: Topic :: Scientific/Engineering
Classifier: Topic :: Scientific/Engineering :: Artificial Intelligence
Classifier: Topic :: Scientific/Engineering :: Information Analysis
Requires-Python: >=3.10
Requires-Dist: jax>=0.4.30
Requires-Dist: jaxlib>=0.4.30
Requires-Dist: matplotlib>=3.8
Requires-Dist: numpy>=1.24
Provides-Extra: dev
Requires-Dist: pytest>=7.0; extra == 'dev'
Provides-Extra: docs
Requires-Dist: mkdocs-material>=9.5; extra == 'docs'
Requires-Dist: mkdocs>=1.5; extra == 'docs'
